ekgtools/__init__.py
ekgtools/config.py
ekgtools/dataset.py
ekgtools/plot.py
ekgtools/s3.py
ekgtools/parser/__init__.py
ekgtools/parser/base.py
ekgtools/parser/eli.py
ekgtools/parser/iecg.py
ekgtools/parser/mimic.py
ekgtools/parser/muse.py
ekgtools/parser/wfdb.py
ekgtools/utils/__init__.py
ekgtools/utils/eli.py
ekgtools/utils/iecg.py
ekgtools/utils/iecg14bit.py
ekgtools/utils/wfdb_func.py
ekgtools-1.0.1.1.dist-info/METADATA
ekgtools-1.0.1.1.dist-info/WHEEL
ekgtools-1.0.1.1.dist-info/top_level.txt
ekgtools-1.0.1.1.dist-info/RECORD
