Metadata-Version: 2.4
Name: ekgtools
Version: 1.0.1.1
Summary: ECG XML parsing, fast loading, and plotting utilities for research pipelines
Author: WYeung, Mat00, FigLing
License: MIT
Keywords: ECG,cardiology,parsing,PyTorch,signal-processing
Classifier: Programming Language :: Python :: 3
Classifier: License :: OSI Approved :: MIT License
Classifier: Operating System :: OS Independent
Classifier: Intended Audience :: Science/Research
Classifier: Topic :: Scientific/Engineering :: Medical Science Apps.
Requires-Python: >=3.10
Requires-Dist: numpy>=1.24
Requires-Dist: pandas>=2.2
Requires-Dist: scipy>=1.11
Requires-Dist: scikit-learn>=1.3
Requires-Dist: xmltodict>=0.13
Requires-Dist: wfdb>=4.1
Requires-Dist: tqdm>=4.65
Requires-Dist: matplotlib>=3.7
Requires-Dist: torch>=2.1
Requires-Dist: torchvision>=0.16
Requires-Dist: fsspec>=2023.12
Requires-Dist: s3fs>=2023.12
Requires-Dist: Pillow>=10.2
Provides-Extra: dev
Requires-Dist: pytest>=7.4; extra == "dev"
Requires-Dist: pytest-cov>=4.1; extra == "dev"
Requires-Dist: ruff>=0.5; extra == "dev"
Requires-Dist: black>=24.3; extra == "dev"
Requires-Dist: mypy>=1.8; extra == "dev"
Requires-Dist: ipykernel>=6.29; extra == "dev"
